{"status": "SUCCESS", "result": {"stats": {"id": "d46ffbb2-84fd-4383-8285-f9159109367e", "algo": "hmmscan", "database": "pfam", "elapsed": 0.05004648119211197, "user": 0.0, "sys": 0.0, "Z": 24076.0, "domZ": 2.0, "Z_setby": 0, "domZ_setby": 0, "nmodels": 24076, "nseqs": 1, "n_past_msv": 692, "n_past_bias": 651, "n_past_vit": 66, "n_past_fwd": 9, "nhits": 2, "nreported": 2, "nincluded": 2, "ngained": null, "nlost": null, "ndropped": null, "first_gained_index": null}, "hits": [{"index": 0, "window_length": 2415993904, "sortkey": 36.330772399902344, "score": 36.330772399902344, "pre_score": 36.374847412109375, "sum_score": 35.424583435058594, "bias": 0.04407501220703125, "lnP": -28.723991953599693, "pre_lnP": -28.755045004677527, "sum_lnP": -28.085536493184122, "nexpected": 1.4218696355819702, "nregions": 1, "nclustered": 0, "noverlaps": 0, "nenvelopes": 1, "ndom": 1, "is_reported": true, "is_included": true, "is_new": false, "is_dropped": false, "nreported": 1, "nincluded": 1, "best_domain": 0, "seqidx": 14366, "subseq_start": 1298174687217846543, "name": "000014366", "acc": "PF01823.24", "evalue": 8.070735805564012e-09, "metadata": {"accession": "PF01823", "identifier": "MACPF", "description": "MAC/Perforin domain", "clan": "CL0293", "type": "Domain", "seq_ga": 21.5, "dom_ga": 21.5, "nested": null, "model_length": 214, "color": "#83daac", "active_sites": null, "external_link": "https://www.ebi.ac.uk/interpro/entry/pfam/PF01823", "clan_link": "https://www.ebi.ac.uk/interpro/set/pfam/CL0293"}, "domains": [{"size": 92, "ienv": 645, "jenv": 762, "iali": 671, "jali": 740, "iorf": 4687146919875718447, "jorf": 4684593656292727399, "envsc": 19.378360748291016, "domcorrection": 2.0715622901916504, "dombias": 0.03055230714380741, "oasc": 91.9662094116211, "bitscore": 35.424583435058594, "lnP": -28.085536493184122, "ievalue": 1.5282373667876615e-08, "cevalue": 1.2695110207573199e-12, "is_reported": true, "is_included": true, "scores_per_pos_length": 0, "scores_per_pos": [], "alignment_display": {"size": 604, "n": 71, "hmmfrom": 33, "hmmto": 101, "m": 214, "sqfrom": 671, "sqto": 740, "l": 909, "string_presence_flags": {"_flagsenum": true, "RFLINE_PRESENT": false, "MMLINE_PRESENT": false, "CSLINE_PRESENT": true, "PPLINE_PRESENT": true, "ASEQ_PRESENT": true, "NTSEQ_PRESENT": false}, "rfline": null, "mmline": null, "csline": "EEEEECETTT-EB-HHHHHHHHCSHSSHHCCCHHH..HHHHHHHHBSEEEEEEEEEEEEEEEEEEEHHCCC", "model": "yqlklkkseklkLseeflkalsaLpsnydkaakat..yiqfidkYGTHyitsvtlGGkivyllkldkskle", "mline": " q+   ++++++ s e+++ + +Lps ++++++++  y+qf+ +YGTH+ t++ lGG +++++  + +  +", "aseq": "IQIAAVDPDRVEVSAEMRNIIARLPS-FSPQSESErqYNQFFTDYGTHVATRLALGGVVRVIIDSKAQVTK", "ntseq": null, "ppline": "344446788999**************.5666666679**********************999875443333", "hmmname": "000014366", "hmmacc": "PF01823.24", "hmmdesc": "{\"i\": \"MACPF\", \"a\": \"PF01823\", \"c\": \"CL0293\", \"d\": \"MAC/Perforin domain\", \"sg\": 21.5, \"dg\": 21.5, \"t\": \"Domain\", \"n\": null, \"l\": 214, \"as\": null, \"cl\": \"#83daac\"}", "sqname": "Unnamed", "sqacc": "", "sqdesc": "query", "identity": [0.2463768115942029, 17], "similarity": [0.7391304347826086, 51]}, "display": true, "outcompeted": false, "significant": true, "uniq": 1, "segments": null, "predicted_active_sites": null}]}, {"index": 1, "window_length": 2550141984, "sortkey": 26.84326171875, "score": 26.84326171875, "pre_score": 27.006492614746094, "sum_score": 24.421354293823242, "bias": 0.16323089599609375, "lnP": -22.178450416682125, "pre_lnP": -22.295119698272146, "sum_lnP": -20.447392104348268, "nexpected": 2.308812141418457, "nregions": 2, "nclustered": 0, "noverlaps": 0, "nenvelopes": 2, "ndom": 2, "is_reported": true, "is_included": true, "is_new": false, "is_dropped": false, "nreported": 1, "nincluded": 1, "best_domain": 0, "seqidx": 15042, "subseq_start": 1298174687217846543, "name": "000015042", "acc": "PF01926.29", "evalue": 5.618310039388992e-06, "metadata": {"accession": "PF01926", "identifier": "MMR_HSR1", "description": "50S ribosome-binding GTPase", "clan": "CL0023", "type": "Family", "seq_ga": 21.9, "dom_ga": 21.9, "nested": null, "model_length": 113, "color": "#357bdb", "active_sites": null, "external_link": "https://www.ebi.ac.uk/interpro/entry/pfam/PF01926", "clan_link": "https://www.ebi.ac.uk/interpro/set/pfam/CL0023"}, "domains": [{"size": 92, "ienv": 287, "jenv": 432, "iali": 289, "jali": 387, "iorf": 4554990195262357504, "jorf": 4575657222458025747, "envsc": 11.705562591552734, "domcorrection": 3.017401695251465, "dombias": 0.07686692476272583, "oasc": 100.13436126708984, "bitscore": 24.421354293823242, "lnP": -20.447392104348268, "ievalue": 3.1724499151328584e-05, "cevalue": 2.6353629466131073e-09, "is_reported": true, "is_included": true, "scores_per_pos_length": 0, "scores_per_pos": [], "alignment_display": {"size": 770, "n": 102, "hmmfrom": 3, "hmmto": 84, "m": 113, "sqfrom": 289, "sqto": 387, "l": 909, "string_presence_flags": {"_flagsenum": true, "RFLINE_PRESENT": false, "MMLINE_PRESENT": false, "CSLINE_PRESENT": true, "PPLINE_PRESENT": true, "ASEQ_PRESENT": true, "NTSEQ_PRESENT": false}, "rfline": null, "mmline": null, "csline": "EEEESTTSSHHHHHHHHHTS..TEEESSSTTSSSSEEEE.EEE.ETTEE.......EEEEECGGC.....SSHCHHHHHHHHHHHH....HHHTSEEEEEEE", "model": "alvGrpNvGKStLinaltgk..kaivsdypgtTrdpneg.kle.lkgkq.......ielvDtpGl.....iegaseeeglerafla....ieeadlillvvd", "mline": " l+G++  GKS  in+l+g+    i +++ g T++++++ k+  + + q       + + DtpGl     + + +++  l++++++    ++  ++illv  ", "aseq": "LLFGQSGHGKSKTINRLIGQdlLPIGESTLGSTTKVIQRvKVLsT-N-QdksatvtVAFDDTPGLddttyL-DRKTNAALMHRYKQkhfeHIFPNVILLVAS", "ntseq": null, "ppline": "689****************97556778888777776555044432.2.235678779999****7666532.455555666666654322333477777664", "hmmname": "000015042", "hmmacc": "PF01926.29", "hmmdesc": "{\"i\": \"MMR_HSR1\", \"a\": \"PF01926\", \"c\": \"CL0023\", \"d\": \"50S ribosome-binding GTPase\", \"sg\": 21.9, \"dg\": 21.9, \"t\": \"Family\", \"n\": null, \"l\": 113, \"as\": null, \"cl\": \"#357bdb\"}", "sqname": "Unnamed", "sqacc": "", "sqdesc": "query", "identity": [0.2926829268292683, 24], "similarity": [0.7195121951219512, 59]}, "display": true, "outcompeted": false, "significant": true, "uniq": 1, "segments": null, "predicted_active_sites": null}, {"size": 92, "ienv": 572, "jenv": 635, "iali": 577, "jali": 610, "iorf": 4575657222490459293, "jorf": 4592018994895935468, "envsc": -6.010702133178711, "domcorrection": 0.40540802478790283, "dombias": 0.005846426822245121, "oasc": 44.84501266479492, "bitscore": -1.4251383543014526, "lnP": -1.9736116936187997, "ievalue": 3345.45865263886, "cevalue": 0.27790817848802624, "is_reported": false, "is_included": false, "scores_per_pos_length": 0, "scores_per_pos": [], "alignment_display": {"size": 435, "n": 35, "hmmfrom": 22, "hmmto": 55, "m": 113, "sqfrom": 577, "sqto": 610, "l": 909, "string_presence_flags": {"_flagsenum": true, "RFLINE_PRESENT": false, "MMLINE_PRESENT": false, "CSLINE_PRESENT": true, "PPLINE_PRESENT": true, "ASEQ_PRESENT": true, "NTSEQ_PRESENT": false}, "rfline": null, "mmline": null, "csline": "S.TEEESSSTTSSSSEEEEEEEETTEEEEEEECGG", "model": "k.kaivsdypgtTrdpnegklelkgkqielvDtpG", "mline": "+ ++i+ +y g T d ++g++  +++ ++l D+p ", "aseq": "RiRQITDSYLGFTYDSKRGTFG-RKSVLRLGDLPI", "ntseq": null, "ppline": "45789999***********998.445788888885", "hmmname": "000015042", "hmmacc": "PF01926.29", "hmmdesc": "{\"i\": \"MMR_HSR1\", \"a\": \"PF01926\", \"c\": \"CL0023\", \"d\": \"50S ribosome-binding GTPase\", \"sg\": 21.9, \"dg\": 21.9, \"t\": \"Family\", \"n\": null, \"l\": 113, \"as\": null, \"cl\": \"#357bdb\"}", "sqname": "Unnamed", "sqacc": "", "sqdesc": "query", "identity": [0.2647058823529412, 9], "similarity": [0.7058823529411765, 24]}, "display": true, "outcompeted": false, "significant": false, "uniq": 1, "segments": null, "predicted_active_sites": null}]}]}, "page_count": 1}