{"status": "SUCCESS", "result": {"stats": {"id": "4caf8e5b-f5f8-491a-949e-f51794dea442", "algo": "hmmscan", "database": "pfam", "elapsed": 0.05848834291100502, "user": 0.0, "sys": 0.0, "Z": 24076.0, "domZ": 1.0, "Z_setby": 0, "domZ_setby": 0, "nmodels": 24076, "nseqs": 1, "n_past_msv": 366, "n_past_bias": 330, "n_past_vit": 13, "n_past_fwd": 1, "nhits": 1, "nreported": 1, "nincluded": 1, "ngained": null, "nlost": null, "ndropped": null, "first_gained_index": null}, "hits": [{"index": 0, "window_length": 2550141984, "sortkey": 46.05231857299805, "score": 46.05231857299805, "pre_score": 46.2484016418457, "sum_score": 44.226314544677734, "bias": 0.19608306884765625, "lnP": -35.95630771989545, "pre_lnP": -36.0973110544046, "sum_lnP": -34.64322822591657, "nexpected": 1.8634976148605347, "nregions": 2, "nclustered": 0, "noverlaps": 0, "nenvelopes": 2, "ndom": 2, "is_reported": true, "is_included": true, "is_new": false, "is_dropped": false, "nreported": 1, "nincluded": 1, "best_domain": 0, "seqidx": 14361, "subseq_start": 1298174687217846543, "name": "000014361", "acc": "PF12464.13", "evalue": 5.8338908892073565e-12, "metadata": {"accession": "PF12464", "identifier": "Mac", "description": "Maltose acetyltransferase hexapeptide capping motif", "clan": null, "type": "Motif", "seq_ga": 22.1, "dom_ga": 22.1, "nested": null, "model_length": 53, "color": "#c03cfe", "active_sites": null, "external_link": "https://www.ebi.ac.uk/interpro/entry/pfam/PF12464", "clan_link": "https://www.ebi.ac.uk/interpro/set/pfam/None"}, "domains": [{"size": 92, "ienv": 22, "jenv": 83, "iali": 22, "jali": 82, "iorf": 13776567383507909452, "jorf": 4458404344682737441, "envsc": 26.486587524414062, "domcorrection": 3.029681921005249, "dombias": 0.07775971293449402, "oasc": 49.79309844970703, "bitscore": 44.226314544677734, "lnP": -34.64322822591657, "ievalue": 2.168809869110575e-11, "cevalue": 9.008181878678248e-16, "is_reported": true, "is_included": true, "scores_per_pos_length": 0, "scores_per_pos": [], "alignment_display": {"size": 578, "n": 61, "hmmfrom": 1, "hmmto": 49, "m": 53, "sqfrom": 22, "sqto": 82, "l": 176, "string_presence_flags": {"_flagsenum": true, "RFLINE_PRESENT": false, "MMLINE_PRESENT": false, "CSLINE_PRESENT": true, "PPLINE_PRESENT": true, "ASEQ_PRESENT": true, "NTSEQ_PRESENT": false}, "rfline": null, "mmline": null, "csline": "HHHTTS-BETTTSHHHHHHHHHHHHHHHHHHT.S...........TTT-HHHHHHHHHHHS", "model": "KMlaGelYdassDpeLvaeRlrarrllrryNn.t...........rpedkeeReelLkell", "mline": "KMl+G++Y a+ D++Lv++Rlr r l+++yN+             ++  ++ R+ +L e++", "aseq": "KMLSGKPYLAMADAQLVKDRLRVRSLMQKYNAyPwpaneadnpdpDYFGPDDRRLILAEIF", "ntseq": null, "ppline": "9******************************944766666555442226666888888888", "hmmname": "000014361", "hmmacc": "PF12464.13", "hmmdesc": "{\"i\": \"Mac\", \"a\": \"PF12464\", \"c\": null, \"d\": \"Maltose acetyltransferase hexapeptide capping motif\", \"sg\": 22.1, \"dg\": 22.1, \"t\": \"Motif\", \"n\": null, \"l\": 53, \"as\": null, \"cl\": \"#c03cfe\"}", "sqname": "Unnamed", "sqacc": "", "sqdesc": "query", "identity": [0.3877551020408163, 19], "similarity": [0.7959183673469388, 39]}, "display": true, "outcompeted": false, "significant": true, "uniq": 1, "segments": null, "predicted_active_sites": null}, {"size": 92, "ienv": 140, "jenv": 160, "iali": 143, "jali": 158, "iorf": 4516871841861218495, "jorf": 4483539367337722032, "envsc": -4.300873279571533, "domcorrection": 0.5877410173416138, "dombias": 0.007009374909102917, "oasc": 15.925533294677734, "bitscore": -1.0882835388183594, "lnP": -2.0575008132191215, "ievalue": 3076.260329275089, "cevalue": 0.12777289953792528, "is_reported": false, "is_included": false, "scores_per_pos_length": 0, "scores_per_pos": [], "alignment_display": {"size": 353, "n": 16, "hmmfrom": 30, "hmmto": 45, "m": 53, "sqfrom": 143, "sqto": 158, "l": 176, "string_presence_flags": {"_flagsenum": true, "RFLINE_PRESENT": false, "MMLINE_PRESENT": false, "CSLINE_PRESENT": true, "PPLINE_PRESENT": true, "ASEQ_PRESENT": true, "NTSEQ_PRESENT": false}, "rfline": null, "mmline": null, "csline": "HHTSTTT-HHHHHHHH", "model": "yNntrpedkeeReelL", "mline": "y +t+ +d +eR++ L", "aseq": "YAATHSTDVAERQKGL", "ntseq": null, "ppline": "6678889999998755", "hmmname": "000014361", "hmmacc": "PF12464.13", "hmmdesc": "{\"i\": \"Mac\", \"a\": \"PF12464\", \"c\": null, \"d\": \"Maltose acetyltransferase hexapeptide capping motif\", \"sg\": 22.1, \"dg\": 22.1, \"t\": \"Motif\", \"n\": null, \"l\": 53, \"as\": null, \"cl\": \"#c03cfe\"}", "sqname": "Unnamed", "sqacc": "", "sqdesc": "query", "identity": [0.375, 6], "similarity": [0.75, 12]}, "display": true, "outcompeted": false, "significant": false, "uniq": 1, "segments": null, "predicted_active_sites": null}]}]}, "page_count": 1}